{
  "associatedLayout": "Cave",
  "name": "CaveFourway",
  "instances": [
    {
      "angle": 0,
      "customSize": false,
      "height": 0,
      "keepRatio": true,
      "layer": "",
      "name": "Up",
      "persistentUuid": "e47ae6c0-7fd9-436a-9285-028b1ba26da7",
      "width": 0,
      "x": 0,
      "y": -1280,
      "zOrder": 4,
      "numberProperties": [],
      "stringProperties": [],
      "initialVariables": []
    },
    {
      "angle": 0,
      "customSize": false,
      "height": 0,
      "keepRatio": true,
      "layer": "",
      "name": "Left",
      "persistentUuid": "0075ef54-ab48-455d-8410-47ad3ab19c8a",
      "width": 0,
      "x": -1280,
      "y": 0,
      "zOrder": 5,
      "numberProperties": [],
      "stringProperties": [],
      "initialVariables": []
    },
    {
      "angle": 0,
      "customSize": false,
      "height": 0,
      "keepRatio": true,
      "layer": "",
      "name": "Right",
      "persistentUuid": "8e96ed0a-d876-482a-876a-5b18c4b75329",
      "width": 0,
      "x": 1280,
      "y": 0,
      "zOrder": 6,
      "numberProperties": [],
      "stringProperties": [],
      "initialVariables": []
    },
    {
      "angle": 0,
      "customSize": false,
      "height": 0,
      "keepRatio": true,
      "layer": "",
      "name": "Down",
      "persistentUuid": "a7be687c-f9cb-4ccd-849f-640f509a6b78",
      "width": 0,
      "x": 0,
      "y": 1280,
      "zOrder": 7,
      "numberProperties": [],
      "stringProperties": [],
      "initialVariables": []
    },
    {
      "angle": 0,
      "customSize": true,
      "depth": 1,
      "height": 1152,
      "layer": "",
      "name": "overlapChecker",
      "persistentUuid": "abac5fab-c1e5-4f87-8ed8-b0cd7ee9a241",
      "width": 1152,
      "x": 64,
      "y": 64,
      "z": -5,
      "zOrder": 8,
      "numberProperties": [],
      "stringProperties": [],
      "initialVariables": []
    },
    {
      "angle": 0,
      "customSize": false,
      "height": 0,
      "keepRatio": true,
      "layer": "",
      "name": "interiorGenerator",
      "persistentUuid": "2b89e1ca-7e4c-48ee-9dae-ad05c83fdae2",
      "width": 0,
      "x": 64,
      "y": 64,
      "zOrder": 10,
      "numberProperties": [],
      "stringProperties": [],
      "initialVariables": []
    },
    {
      "angle": 0,
      "customSize": false,
      "height": 0,
      "keepRatio": true,
      "layer": "",
      "name": "CaveWall",
      "persistentUuid": "631e4bb1-3516-4e73-8ec9-763348405c41",
      "width": 0,
      "x": 31,
      "y": 64,
      "zOrder": 11,
      "numberProperties": [],
      "stringProperties": [],
      "initialVariables": []
    },
    {
      "angle": 0,
      "customSize": false,
      "height": 0,
      "keepRatio": true,
      "layer": "",
      "name": "CaveWall",
      "persistentUuid": "eaeaca87-ee14-4bc4-9c55-dee504d36905",
      "width": 0,
      "x": 95,
      "y": 64,
      "zOrder": 11,
      "numberProperties": [],
      "stringProperties": [],
      "initialVariables": []
    },
    {
      "angle": 0,
      "customSize": true,
      "depth": 63,
      "height": 64,
      "keepRatio": true,
      "layer": "",
      "name": "CaveWall",
      "persistentUuid": "d088a609-59da-4a28-9f89-85411b03e5ff",
      "width": 64,
      "x": 160,
      "y": 64,
      "zOrder": 11,
      "numberProperties": [],
      "stringProperties": [],
      "initialVariables": []
    },
    {
      "angle": 0,
      "customSize": false,
      "height": 0,
      "keepRatio": true,
      "layer": "",
      "name": "CaveWall",
      "persistentUuid": "1bf9fff0-d88a-4002-8dcb-45e2a85466cc",
      "width": 0,
      "x": 223,
      "y": 64,
      "zOrder": 11,
      "numberProperties": [],
      "stringProperties": [],
      "initialVariables": []
    },
    {
      "angle": 0,
      "customSize": false,
      "height": 0,
      "keepRatio": true,
      "layer": "",
      "name": "CaveWall",
      "persistentUuid": "ff14bde3-629d-4c88-826c-3395e3a84cbb",
      "width": 0,
      "x": 287,
      "y": 64,
      "zOrder": 11,
      "numberProperties": [],
      "stringProperties": [],
      "initialVariables": []
    },
    {
      "angle": 0,
      "customSize": false,
      "height": 0,
      "keepRatio": true,
      "layer": "",
      "name": "CaveWall",
      "persistentUuid": "7bd6b8a1-a7d6-478a-9a43-f0b99de5e10d",
      "width": 0,
      "x": 351,
      "y": 64,
      "zOrder": 11,
      "numberProperties": [],
      "stringProperties": [],
      "initialVariables": []
    },
    {
      "angle": 0,
      "customSize": false,
      "height": 0,
      "keepRatio": true,
      "layer": "",
      "name": "CaveWall",
      "persistentUuid": "1bf70b40-c24c-4df1-9347-b5531856aa43",
      "width": 0,
      "x": 415,
      "y": 64,
      "zOrder": 11,
      "numberProperties": [],
      "stringProperties": [],
      "initialVariables": []
    },
    {
      "angle": 0,
      "customSize": false,
      "height": 0,
      "keepRatio": true,
      "layer": "",
      "name": "CaveWall",
      "persistentUuid": "6c2c675b-d57d-471d-a9f6-39d780ef60bf",
      "width": 0,
      "x": 479,
      "y": 64,
      "zOrder": 11,
      "numberProperties": [],
      "stringProperties": [],
      "initialVariables": []
    },
    {
      "angle": 0,
      "customSize": false,
      "height": 0,
      "keepRatio": true,
      "layer": "",
      "name": "CaveWall",
      "persistentUuid": "2a11c229-09fa-4cb3-a0f0-b034e23342f0",
      "width": 0,
      "x": 543,
      "y": 64,
      "zOrder": 11,
      "numberProperties": [],
      "stringProperties": [],
      "initialVariables": []
    },
    {
      "angle": 0,
      "customSize": false,
      "height": 0,
      "keepRatio": true,
      "layer": "",
      "name": "CaveWall",
      "persistentUuid": "1c466de7-3e0f-4932-8a5c-39328d88c4aa",
      "width": 0,
      "x": 735,
      "y": 64,
      "zOrder": 11,
      "numberProperties": [],
      "stringProperties": [],
      "initialVariables": []
    },
    {
      "angle": 0,
      "customSize": false,
      "height": 0,
      "keepRatio": true,
      "layer": "",
      "name": "CaveWall",
      "persistentUuid": "424dd415-f69b-4ed8-a034-fa4ef9197b80",
      "width": 0,
      "x": 799,
      "y": 64,
      "zOrder": 11,
      "numberProperties": [],
      "stringProperties": [],
      "initialVariables": []
    },
    {
      "angle": 0,
      "customSize": false,
      "height": 0,
      "keepRatio": true,
      "layer": "",
      "name": "CaveWall",
      "persistentUuid": "39a01a16-7080-4383-ba3f-7ad6be4326f7",
      "width": 0,
      "x": 865,
      "y": 64,
      "zOrder": 11,
      "numberProperties": [],
      "stringProperties": [],
      "initialVariables": []
    },
    {
      "angle": 0,
      "customSize": false,
      "height": 0,
      "keepRatio": true,
      "layer": "",
      "name": "CaveWall",
      "persistentUuid": "99208b26-d813-4fe9-baac-3e9ad306bd1d",
      "width": 0,
      "x": 929,
      "y": 64,
      "zOrder": 11,
      "numberProperties": [],
      "stringProperties": [],
      "initialVariables": []
    },
    {
      "angle": 0,
      "customSize": false,
      "height": 0,
      "keepRatio": true,
      "layer": "",
      "name": "CaveWall",
      "persistentUuid": "1b8f05af-9682-49ae-b1cd-74bbc20de11e",
      "width": 0,
      "x": 991,
      "y": 64,
      "zOrder": 11,
      "numberProperties": [],
      "stringProperties": [],
      "initialVariables": []
    },
    {
      "angle": 0,
      "customSize": false,
      "height": 0,
      "keepRatio": true,
      "layer": "",
      "name": "CaveWall",
      "persistentUuid": "e1b2f85f-5aaf-4180-b428-190757d6a08a",
      "width": 0,
      "x": 1055,
      "y": 64,
      "zOrder": 11,
      "numberProperties": [],
      "stringProperties": [],
      "initialVariables": []
    },
    {
      "angle": 0,
      "customSize": false,
      "height": 0,
      "keepRatio": true,
      "layer": "",
      "name": "CaveWall",
      "persistentUuid": "b4b86af9-a284-4362-a7c8-e18495f742e0",
      "width": 0,
      "x": 1119,
      "y": 64,
      "zOrder": 11,
      "numberProperties": [],
      "stringProperties": [],
      "initialVariables": []
    },
    {
      "angle": 0,
      "customSize": false,
      "height": 0,
      "keepRatio": true,
      "layer": "",
      "name": "CaveWall",
      "persistentUuid": "90336597-ca20-43d3-90f4-10fa36d39107",
      "width": 0,
      "x": 1183,
      "y": 64,
      "zOrder": 11,
      "numberProperties": [],
      "stringProperties": [],
      "initialVariables": []
    },
    {
      "angle": 90,
      "customSize": false,
      "height": 0,
      "keepRatio": true,
      "layer": "",
      "name": "CaveWall",
      "persistentUuid": "8ffd28a4-d801-4a92-ae42-cb03b51f8c02",
      "width": 0,
      "x": 1216,
      "y": 33,
      "zOrder": 11,
      "numberProperties": [],
      "stringProperties": [],
      "initialVariables": []
    },
    {
      "angle": 90,
      "customSize": false,
      "height": 0,
      "keepRatio": true,
      "layer": "",
      "name": "CaveWall",
      "persistentUuid": "6d385f0b-6080-4b52-930a-da287a3653e6",
      "width": 0,
      "x": 1216,
      "y": 95,
      "zOrder": 11,
      "numberProperties": [],
      "stringProperties": [],
      "initialVariables": []
    },
    {
      "angle": 90,
      "customSize": true,
      "depth": 63,
      "height": 64,
      "keepRatio": true,
      "layer": "",
      "name": "CaveWall",
      "persistentUuid": "03053b89-ba0b-4c36-b7a6-3e066016b629",
      "width": 64,
      "x": 1216,
      "y": 159,
      "zOrder": 11,
      "numberProperties": [],
      "stringProperties": [],
      "initialVariables": []
    },
    {
      "angle": 90,
      "customSize": false,
      "height": 0,
      "keepRatio": true,
      "layer": "",
      "name": "CaveWall",
      "persistentUuid": "37c5346d-e725-48fb-be6f-3d39093e3995",
      "width": 0,
      "x": 1216,
      "y": 223,
      "zOrder": 11,
      "numberProperties": [],
      "stringProperties": [],
      "initialVariables": []
    },
    {
      "angle": 90,
      "customSize": false,
      "height": 0,
      "keepRatio": true,
      "layer": "",
      "name": "CaveWall",
      "persistentUuid": "76ecae3b-b31b-4a88-93ad-6bbb479ac3c4",
      "width": 0,
      "x": 1216,
      "y": 287,
      "zOrder": 11,
      "numberProperties": [],
      "stringProperties": [],
      "initialVariables": []
    },
    {
      "angle": 90,
      "customSize": false,
      "height": 0,
      "keepRatio": true,
      "layer": "",
      "name": "CaveWall",
      "persistentUuid": "08602e9b-a2c1-4943-839b-2a39e6ccc2ae",
      "width": 0,
      "x": 1216,
      "y": 351,
      "zOrder": 11,
      "numberProperties": [],
      "stringProperties": [],
      "initialVariables": []
    },
    {
      "angle": 90,
      "customSize": false,
      "height": 0,
      "keepRatio": true,
      "layer": "",
      "name": "CaveWall",
      "persistentUuid": "2dc64342-66c5-4b56-ba75-9f9fbb1c6f8e",
      "width": 0,
      "x": 1216,
      "y": 415,
      "zOrder": 11,
      "numberProperties": [],
      "stringProperties": [],
      "initialVariables": []
    },
    {
      "angle": 90,
      "customSize": false,
      "height": 0,
      "keepRatio": true,
      "layer": "",
      "name": "CaveWall",
      "persistentUuid": "d4d839ed-8bad-4978-aa23-6e5cf792266d",
      "width": 0,
      "x": 1216,
      "y": 479,
      "zOrder": 11,
      "numberProperties": [],
      "stringProperties": [],
      "initialVariables": []
    },
    {
      "angle": 90,
      "customSize": false,
      "height": 0,
      "keepRatio": true,
      "layer": "",
      "name": "CaveWall",
      "persistentUuid": "074bd39b-0ef3-4c7c-9deb-d60391314657",
      "width": 0,
      "x": 1216,
      "y": 543,
      "zOrder": 11,
      "numberProperties": [],
      "stringProperties": [],
      "initialVariables": []
    },
    {
      "angle": 90,
      "customSize": false,
      "height": 0,
      "keepRatio": true,
      "layer": "",
      "name": "CaveWall",
      "persistentUuid": "249b8239-ca35-4b4b-9b9c-dbafbebd5e20",
      "width": 0,
      "x": 1216,
      "y": 735,
      "zOrder": 11,
      "numberProperties": [],
      "stringProperties": [],
      "initialVariables": []
    },
    {
      "angle": 90,
      "customSize": false,
      "height": 0,
      "keepRatio": true,
      "layer": "",
      "name": "CaveWall",
      "persistentUuid": "c4921491-3a5e-4367-8879-82aed46129e9",
      "width": 0,
      "x": 1216,
      "y": 799,
      "zOrder": 11,
      "numberProperties": [],
      "stringProperties": [],
      "initialVariables": []
    },
    {
      "angle": 90,
      "customSize": false,
      "height": 0,
      "keepRatio": true,
      "layer": "",
      "name": "CaveWall",
      "persistentUuid": "3a74026c-4a59-46f8-9a8e-7eeb3bd0fec1",
      "width": 0,
      "x": 1216,
      "y": 863,
      "zOrder": 11,
      "numberProperties": [],
      "stringProperties": [],
      "initialVariables": []
    },
    {
      "angle": 90,
      "customSize": false,
      "height": 0,
      "keepRatio": true,
      "layer": "",
      "name": "CaveWall",
      "persistentUuid": "09bfbff3-2945-4bd6-babd-1ce48abd7522",
      "width": 0,
      "x": 1216,
      "y": 927,
      "zOrder": 11,
      "numberProperties": [],
      "stringProperties": [],
      "initialVariables": []
    },
    {
      "angle": 90,
      "customSize": false,
      "height": 0,
      "keepRatio": true,
      "layer": "",
      "name": "CaveWall",
      "persistentUuid": "367835b9-c240-4047-9858-0dc5064a053a",
      "width": 0,
      "x": 1216,
      "y": 991,
      "zOrder": 11,
      "numberProperties": [],
      "stringProperties": [],
      "initialVariables": []
    },
    {
      "angle": 90,
      "customSize": false,
      "height": 0,
      "keepRatio": true,
      "layer": "",
      "name": "CaveWall",
      "persistentUuid": "4dbcc2af-1894-4d43-a8ca-9e6cdafed2c1",
      "width": 0,
      "x": 1216,
      "y": 1055,
      "zOrder": 11,
      "numberProperties": [],
      "stringProperties": [],
      "initialVariables": []
    },
    {
      "angle": 90,
      "customSize": false,
      "height": 0,
      "keepRatio": true,
      "layer": "",
      "name": "CaveWall",
      "persistentUuid": "dcf0fa63-4970-4326-9c35-c2294d0ad4ae",
      "width": 0,
      "x": 1216,
      "y": 1119,
      "zOrder": 11,
      "numberProperties": [],
      "stringProperties": [],
      "initialVariables": []
    },
    {
      "angle": 90,
      "customSize": false,
      "height": 0,
      "keepRatio": true,
      "layer": "",
      "name": "CaveWall",
      "persistentUuid": "bd6b4df0-65bc-4057-b6b8-eae261f02766",
      "width": 0,
      "x": 1216,
      "y": 1183,
      "zOrder": 11,
      "numberProperties": [],
      "stringProperties": [],
      "initialVariables": []
    },
    {
      "angle": 0,
      "customSize": false,
      "height": 0,
      "keepRatio": true,
      "layer": "",
      "name": "CaveWall",
      "persistentUuid": "7e308a02-13bb-4062-98df-b8e188f54fb2",
      "width": 0,
      "x": 95,
      "y": 1280,
      "zOrder": 11,
      "numberProperties": [],
      "stringProperties": [],
      "initialVariables": []
    },
    {
      "angle": 0,
      "customSize": false,
      "height": 0,
      "keepRatio": true,
      "layer": "",
      "name": "CaveWall",
      "persistentUuid": "4ccfd5eb-eff4-4bb6-af2b-5f133826d248",
      "width": 0,
      "x": 159,
      "y": 1280,
      "zOrder": 11,
      "numberProperties": [],
      "stringProperties": [],
      "initialVariables": []
    },
    {
      "angle": 0,
      "customSize": true,
      "depth": 63,
      "height": 64,
      "keepRatio": true,
      "layer": "",
      "name": "CaveWall",
      "persistentUuid": "a26d61ac-943a-4c50-bc03-9f1efee60088",
      "width": 64,
      "x": 223,
      "y": 1280,
      "zOrder": 11,
      "numberProperties": [],
      "stringProperties": [],
      "initialVariables": []
    },
    {
      "angle": 0,
      "customSize": false,
      "height": 0,
      "keepRatio": true,
      "layer": "",
      "name": "CaveWall",
      "persistentUuid": "d7ac092b-2456-4b2c-bf64-f2192306cb4b",
      "width": 0,
      "x": 287,
      "y": 1280,
      "zOrder": 11,
      "numberProperties": [],
      "stringProperties": [],
      "initialVariables": []
    },
    {
      "angle": 0,
      "customSize": false,
      "height": 0,
      "keepRatio": true,
      "layer": "",
      "name": "CaveWall",
      "persistentUuid": "9e1a1ba9-9a50-419c-aa5f-d3087b361d2a",
      "width": 0,
      "x": 351,
      "y": 1280,
      "zOrder": 11,
      "numberProperties": [],
      "stringProperties": [],
      "initialVariables": []
    },
    {
      "angle": 0,
      "customSize": false,
      "height": 0,
      "keepRatio": true,
      "layer": "",
      "name": "CaveWall",
      "persistentUuid": "29441068-fa35-4965-ac32-a26a5c76c8a7",
      "width": 0,
      "x": 415,
      "y": 1280,
      "zOrder": 11,
      "numberProperties": [],
      "stringProperties": [],
      "initialVariables": []
    },
    {
      "angle": 0,
      "customSize": false,
      "height": 0,
      "keepRatio": true,
      "layer": "",
      "name": "CaveWall",
      "persistentUuid": "031bd832-0cec-4716-bb00-ab5c310d6bf2",
      "width": 0,
      "x": 479,
      "y": 1280,
      "zOrder": 11,
      "numberProperties": [],
      "stringProperties": [],
      "initialVariables": []
    },
    {
      "angle": 0,
      "customSize": false,
      "height": 0,
      "keepRatio": true,
      "layer": "",
      "name": "CaveWall",
      "persistentUuid": "9934e833-6635-410a-8f1e-8fcfeacf4b23",
      "width": 0,
      "x": 543,
      "y": 1280,
      "zOrder": 11,
      "numberProperties": [],
      "stringProperties": [],
      "initialVariables": []
    },
    {
      "angle": 0,
      "customSize": false,
      "height": 0,
      "keepRatio": true,
      "layer": "",
      "name": "CaveWall",
      "persistentUuid": "6914f018-e004-4ba9-b90d-b5c01900ef88",
      "width": 0,
      "x": 735,
      "y": 1280,
      "zOrder": 11,
      "numberProperties": [],
      "stringProperties": [],
      "initialVariables": []
    },
    {
      "angle": 0,
      "customSize": false,
      "height": 0,
      "keepRatio": true,
      "layer": "",
      "name": "CaveWall",
      "persistentUuid": "17409b4b-ef4b-4e61-8e8b-d3064a9aa02b",
      "width": 0,
      "x": 799,
      "y": 1280,
      "zOrder": 11,
      "numberProperties": [],
      "stringProperties": [],
      "initialVariables": []
    },
    {
      "angle": 0,
      "customSize": false,
      "height": 0,
      "keepRatio": true,
      "layer": "",
      "name": "CaveWall",
      "persistentUuid": "b350cdfc-9239-402e-9046-ad3156d945c7",
      "width": 0,
      "x": 863,
      "y": 1280,
      "zOrder": 11,
      "numberProperties": [],
      "stringProperties": [],
      "initialVariables": []
    },
    {
      "angle": 0,
      "customSize": false,
      "height": 0,
      "keepRatio": true,
      "layer": "",
      "name": "CaveWall",
      "persistentUuid": "e3b23aa7-15dc-43e4-a404-5a4a0e51dcc0",
      "width": 0,
      "x": 927,
      "y": 1280,
      "zOrder": 11,
      "numberProperties": [],
      "stringProperties": [],
      "initialVariables": []
    },
    {
      "angle": 0,
      "customSize": false,
      "height": 0,
      "keepRatio": true,
      "layer": "",
      "name": "CaveWall",
      "persistentUuid": "6b8c4a15-2403-45b7-96c3-e81a6aab4b5b",
      "width": 0,
      "x": 991,
      "y": 1280,
      "zOrder": 11,
      "numberProperties": [],
      "stringProperties": [],
      "initialVariables": []
    },
    {
      "angle": 0,
      "customSize": false,
      "height": 0,
      "keepRatio": true,
      "layer": "",
      "name": "CaveWall",
      "persistentUuid": "ea893473-b2b6-4822-ab85-c24a40645786",
      "width": 0,
      "x": 1055,
      "y": 1280,
      "zOrder": 11,
      "numberProperties": [],
      "stringProperties": [],
      "initialVariables": []
    },
    {
      "angle": 0,
      "customSize": false,
      "height": 0,
      "keepRatio": true,
      "layer": "",
      "name": "CaveWall",
      "persistentUuid": "281dcf64-07b8-4d44-8a05-f7a148ff884b",
      "width": 0,
      "x": 1119,
      "y": 1280,
      "zOrder": 11,
      "numberProperties": [],
      "stringProperties": [],
      "initialVariables": []
    },
    {
      "angle": 0,
      "customSize": false,
      "height": 0,
      "keepRatio": true,
      "layer": "",
      "name": "CaveWall",
      "persistentUuid": "b637e155-a97e-4f1c-bf28-f547e99e42f5",
      "width": 0,
      "x": 1183,
      "y": 1280,
      "zOrder": 11,
      "numberProperties": [],
      "stringProperties": [],
      "initialVariables": []
    },
    {
      "angle": 0,
      "customSize": false,
      "height": 0,
      "keepRatio": true,
      "layer": "",
      "name": "CaveWall",
      "persistentUuid": "b3e58744-5536-4b25-9edc-133cf8a2a74c",
      "width": 0,
      "x": 1247,
      "y": 1280,
      "zOrder": 11,
      "numberProperties": [],
      "stringProperties": [],
      "initialVariables": []
    },
    {
      "angle": 90,
      "customSize": false,
      "height": 0,
      "keepRatio": true,
      "layer": "",
      "name": "CaveWall",
      "persistentUuid": "1d11e0aa-1ddd-4df4-ae01-a225ffad65df",
      "width": 0,
      "x": 0,
      "y": 95,
      "zOrder": 11,
      "numberProperties": [],
      "stringProperties": [],
      "initialVariables": []
    },
    {
      "angle": 90,
      "customSize": false,
      "height": 0,
      "keepRatio": true,
      "layer": "",
      "name": "CaveWall",
      "persistentUuid": "6524c74a-0915-4349-a371-91bf7f817339",
      "width": 0,
      "x": 0,
      "y": 159,
      "zOrder": 11,
      "numberProperties": [],
      "stringProperties": [],
      "initialVariables": []
    },
    {
      "angle": 90,
      "customSize": true,
      "depth": 63,
      "height": 64,
      "keepRatio": true,
      "layer": "",
      "name": "CaveWall",
      "persistentUuid": "3a372b31-3e28-4445-ba60-6017cdb7c4f7",
      "width": 64,
      "x": 0,
      "y": 223,
      "zOrder": 11,
      "numberProperties": [],
      "stringProperties": [],
      "initialVariables": []
    },
    {
      "angle": 90,
      "customSize": false,
      "height": 0,
      "keepRatio": true,
      "layer": "",
      "name": "CaveWall",
      "persistentUuid": "74147532-0afb-469a-b8ac-0e5ee9e4601a",
      "width": 0,
      "x": 0,
      "y": 287,
      "zOrder": 11,
      "numberProperties": [],
      "stringProperties": [],
      "initialVariables": []
    },
    {
      "angle": 90,
      "customSize": false,
      "height": 0,
      "keepRatio": true,
      "layer": "",
      "name": "CaveWall",
      "persistentUuid": "471f63cb-8ade-41fb-8501-bf2869c6c261",
      "width": 0,
      "x": 0,
      "y": 351,
      "zOrder": 11,
      "numberProperties": [],
      "stringProperties": [],
      "initialVariables": []
    },
    {
      "angle": 90,
      "customSize": false,
      "height": 0,
      "keepRatio": true,
      "layer": "",
      "name": "CaveWall",
      "persistentUuid": "5cc5eee8-6195-401c-be59-2bbbe990783a",
      "width": 0,
      "x": 0,
      "y": 415,
      "zOrder": 11,
      "numberProperties": [],
      "stringProperties": [],
      "initialVariables": []
    },
    {
      "angle": 90,
      "customSize": false,
      "height": 0,
      "keepRatio": true,
      "layer": "",
      "name": "CaveWall",
      "persistentUuid": "dedd8e92-4b2c-4c3d-8332-d51902cbebfa",
      "width": 0,
      "x": 0,
      "y": 479,
      "zOrder": 11,
      "numberProperties": [],
      "stringProperties": [],
      "initialVariables": []
    },
    {
      "angle": 90,
      "customSize": false,
      "height": 0,
      "keepRatio": true,
      "layer": "",
      "name": "CaveWall",
      "persistentUuid": "d8b87c66-79c4-49ff-8e9d-65a1706f1b52",
      "width": 0,
      "x": 0,
      "y": 543,
      "zOrder": 11,
      "numberProperties": [],
      "stringProperties": [],
      "initialVariables": []
    },
    {
      "angle": 90,
      "customSize": false,
      "height": 0,
      "keepRatio": true,
      "layer": "",
      "name": "CaveWall",
      "persistentUuid": "505bc1ed-e64c-470e-ad65-39e5c5b4df45",
      "width": 0,
      "x": 0,
      "y": 735,
      "zOrder": 11,
      "numberProperties": [],
      "stringProperties": [],
      "initialVariables": []
    },
    {
      "angle": 90,
      "customSize": false,
      "height": 0,
      "keepRatio": true,
      "layer": "",
      "name": "CaveWall",
      "persistentUuid": "593031f5-4b97-4f00-b1c4-5b7721e3a29b",
      "width": 0,
      "x": 0,
      "y": 799,
      "zOrder": 11,
      "numberProperties": [],
      "stringProperties": [],
      "initialVariables": []
    },
    {
      "angle": 90,
      "customSize": false,
      "height": 0,
      "keepRatio": true,
      "layer": "",
      "name": "CaveWall",
      "persistentUuid": "9b69ee8b-5fc8-48c0-b0b3-6d57ea131689",
      "width": 0,
      "x": 0,
      "y": 863,
      "zOrder": 11,
      "numberProperties": [],
      "stringProperties": [],
      "initialVariables": []
    },
    {
      "angle": 90,
      "customSize": false,
      "height": 0,
      "keepRatio": true,
      "layer": "",
      "name": "CaveWall",
      "persistentUuid": "486a00a2-540a-4ace-90ed-113faa675eca",
      "width": 0,
      "x": 0,
      "y": 927,
      "zOrder": 11,
      "numberProperties": [],
      "stringProperties": [],
      "initialVariables": []
    },
    {
      "angle": 90,
      "customSize": false,
      "height": 0,
      "keepRatio": true,
      "layer": "",
      "name": "CaveWall",
      "persistentUuid": "6bdb7f09-2587-4902-abe3-3486b7bc2c02",
      "width": 0,
      "x": 0,
      "y": 991,
      "zOrder": 11,
      "numberProperties": [],
      "stringProperties": [],
      "initialVariables": []
    },
    {
      "angle": 90,
      "customSize": false,
      "height": 0,
      "keepRatio": true,
      "layer": "",
      "name": "CaveWall",
      "persistentUuid": "21e8c9ac-e629-4ea1-9835-e744cdabba09",
      "width": 0,
      "x": 0,
      "y": 1055,
      "zOrder": 11,
      "numberProperties": [],
      "stringProperties": [],
      "initialVariables": []
    },
    {
      "angle": 90,
      "customSize": false,
      "height": 0,
      "keepRatio": true,
      "layer": "",
      "name": "CaveWall",
      "persistentUuid": "2f3a0094-6653-4d89-8170-a2e89a26777d",
      "width": 0,
      "x": 0,
      "y": 1119,
      "zOrder": 11,
      "numberProperties": [],
      "stringProperties": [],
      "initialVariables": []
    },
    {
      "angle": 90,
      "customSize": false,
      "height": 0,
      "keepRatio": true,
      "layer": "",
      "name": "CaveWall",
      "persistentUuid": "5e7c0357-ab02-42f5-9111-f8c92064c1fe",
      "width": 0,
      "x": 0,
      "y": 1183,
      "zOrder": 11,
      "numberProperties": [],
      "stringProperties": [],
      "initialVariables": []
    },
    {
      "angle": 90,
      "customSize": false,
      "height": 0,
      "keepRatio": true,
      "layer": "",
      "name": "CaveWall",
      "persistentUuid": "e34db0e3-46d4-45d4-bbb5-acd5149cda71",
      "width": 0,
      "x": 0,
      "y": 1247,
      "zOrder": 11,
      "numberProperties": [],
      "stringProperties": [],
      "initialVariables": []
    },
    {
      "angle": 0,
      "customSize": false,
      "height": 0,
      "keepRatio": true,
      "layer": "",
      "name": "CaveFloor",
      "persistentUuid": "18c29fa4-12d8-4cce-8ce5-48ece21b979b",
      "width": 0,
      "x": 768,
      "y": -64,
      "zOrder": 12,
      "numberProperties": [],
      "stringProperties": [],
      "initialVariables": []
    }
  ],
  "editionSettings": {
    "grid": true,
    "gridType": "rectangular",
    "gridWidth": 64,
    "gridHeight": 64,
    "gridOffsetX": 0,
    "gridOffsetY": 0,
    "gridColor": 10401023,
    "gridAlpha": 0.8,
    "snap": true,
    "zoomFactor": 0.5147058823529446,
    "windowMask": false
  }
}