{
  "associatedLayout": "Forest",
  "name": "ExFourWay",
  "instances": [
    {
      "angle": 0,
      "customSize": false,
      "height": 0,
      "keepRatio": true,
      "layer": "",
      "name": "Wall",
      "persistentUuid": "807d6270-da55-4dea-8a2f-ffa451425dc0",
      "width": 0,
      "x": 32,
      "y": 32,
      "zOrder": 1,
      "numberProperties": [],
      "stringProperties": [],
      "initialVariables": []
    },
    {
      "angle": 0,
      "customSize": false,
      "height": 0,
      "keepRatio": true,
      "layer": "",
      "name": "Wall",
      "persistentUuid": "025daa66-893f-495b-b1f2-5b0d06bbce91",
      "width": 0,
      "x": 96,
      "y": 32,
      "zOrder": 1,
      "numberProperties": [],
      "stringProperties": [],
      "initialVariables": []
    },
    {
      "angle": 0,
      "customSize": false,
      "height": 0,
      "keepRatio": true,
      "layer": "",
      "name": "Wall",
      "persistentUuid": "e74e8219-7486-49e9-8d94-aaa409cd3cf3",
      "width": 0,
      "x": 160,
      "y": 32,
      "zOrder": 1,
      "numberProperties": [],
      "stringProperties": [],
      "initialVariables": []
    },
    {
      "angle": 0,
      "customSize": false,
      "height": 0,
      "keepRatio": true,
      "layer": "",
      "name": "Wall",
      "persistentUuid": "d468c163-c409-4c25-b399-fc5980c611a8",
      "width": 0,
      "x": 224,
      "y": 32,
      "zOrder": 1,
      "numberProperties": [],
      "stringProperties": [],
      "initialVariables": []
    },
    {
      "angle": 0,
      "customSize": false,
      "height": 0,
      "keepRatio": true,
      "layer": "",
      "name": "Wall",
      "persistentUuid": "8ade12e0-0c94-467d-92f1-e8227edd01ff",
      "width": 0,
      "x": 288,
      "y": 32,
      "zOrder": 1,
      "numberProperties": [],
      "stringProperties": [],
      "initialVariables": []
    },
    {
      "angle": 0,
      "customSize": false,
      "height": 0,
      "keepRatio": true,
      "layer": "",
      "name": "Wall",
      "persistentUuid": "a9f8a94c-7df6-4fa9-b74f-a360b5a7be59",
      "width": 0,
      "x": 352,
      "y": 32,
      "zOrder": 1,
      "numberProperties": [],
      "stringProperties": [],
      "initialVariables": []
    },
    {
      "angle": 0,
      "customSize": false,
      "height": 0,
      "keepRatio": true,
      "layer": "",
      "name": "Wall",
      "persistentUuid": "8f939cee-8b1d-4913-92c0-19ee23cdafe5",
      "width": 0,
      "x": 416,
      "y": 32,
      "zOrder": 1,
      "numberProperties": [],
      "stringProperties": [],
      "initialVariables": []
    },
    {
      "angle": 0,
      "customSize": false,
      "height": 0,
      "keepRatio": true,
      "layer": "",
      "name": "Wall",
      "persistentUuid": "df37dc86-14fe-45d4-be84-bb3a1d4973ff",
      "width": 0,
      "x": 480,
      "y": 32,
      "zOrder": 1,
      "numberProperties": [],
      "stringProperties": [],
      "initialVariables": []
    },
    {
      "angle": 90,
      "customSize": false,
      "height": 0,
      "keepRatio": true,
      "layer": "",
      "name": "Wall",
      "persistentUuid": "a542a63b-3b84-42ae-98db-f80ce548c50a",
      "width": 0,
      "x": 32,
      "y": 96,
      "zOrder": 1,
      "numberProperties": [],
      "stringProperties": [],
      "initialVariables": []
    },
    {
      "angle": 90,
      "customSize": false,
      "height": 0,
      "keepRatio": true,
      "layer": "",
      "name": "Wall",
      "persistentUuid": "8e3f6474-c8d9-4727-9f97-f92f405e2294",
      "width": 0,
      "x": 32,
      "y": 160,
      "zOrder": 1,
      "numberProperties": [],
      "stringProperties": [],
      "initialVariables": []
    },
    {
      "angle": 90,
      "customSize": false,
      "height": 0,
      "keepRatio": true,
      "layer": "",
      "name": "Wall",
      "persistentUuid": "d943fcac-f9eb-4cee-8e10-dad50b11ceb6",
      "width": 0,
      "x": 32,
      "y": 224,
      "zOrder": 1,
      "numberProperties": [],
      "stringProperties": [],
      "initialVariables": []
    },
    {
      "angle": 90,
      "customSize": false,
      "height": 0,
      "keepRatio": true,
      "layer": "",
      "name": "Wall",
      "persistentUuid": "22d16224-81e6-4867-aad7-fa48b26598f7",
      "width": 0,
      "x": 32,
      "y": 288,
      "zOrder": 1,
      "numberProperties": [],
      "stringProperties": [],
      "initialVariables": []
    },
    {
      "angle": 90,
      "customSize": false,
      "height": 0,
      "keepRatio": true,
      "layer": "",
      "name": "Wall",
      "persistentUuid": "8a6f1008-7684-4abb-9193-c186216558ee",
      "width": 0,
      "x": 32,
      "y": 352,
      "zOrder": 1,
      "numberProperties": [],
      "stringProperties": [],
      "initialVariables": []
    },
    {
      "angle": 90,
      "customSize": false,
      "height": 0,
      "keepRatio": true,
      "layer": "",
      "name": "Wall",
      "persistentUuid": "4083924b-e230-468b-a757-f2775f1d7c50",
      "width": 0,
      "x": 32,
      "y": 416,
      "zOrder": 1,
      "numberProperties": [],
      "stringProperties": [],
      "initialVariables": []
    },
    {
      "angle": 90,
      "customSize": false,
      "height": 0,
      "keepRatio": true,
      "layer": "",
      "name": "Wall",
      "persistentUuid": "6d3e2b42-05b4-48bf-9946-cd6f6613f04f",
      "width": 0,
      "x": 32,
      "y": 480,
      "zOrder": 1,
      "numberProperties": [],
      "stringProperties": [],
      "initialVariables": []
    },
    {
      "angle": 90,
      "customSize": false,
      "height": 0,
      "keepRatio": true,
      "layer": "",
      "name": "Wall",
      "persistentUuid": "e0ba49e5-2dca-41ab-9133-2bf22f2a2f52",
      "width": 0,
      "x": 32,
      "y": 544,
      "zOrder": 1,
      "numberProperties": [],
      "stringProperties": [],
      "initialVariables": []
    },
    {
      "angle": 0,
      "customSize": false,
      "height": 0,
      "keepRatio": true,
      "layer": "",
      "name": "Wall",
      "persistentUuid": "7171a855-cfff-4842-8b72-654b42626e10",
      "width": 0,
      "x": 544,
      "y": 32,
      "zOrder": 1,
      "numberProperties": [],
      "stringProperties": [],
      "initialVariables": []
    },
    {
      "angle": 270,
      "customSize": false,
      "height": 0,
      "keepRatio": true,
      "layer": "",
      "name": "Wall",
      "persistentUuid": "107e87da-c82e-450a-936f-036b9ea9b1e6",
      "width": 0,
      "x": 32,
      "y": 1248,
      "zOrder": 1,
      "numberProperties": [],
      "stringProperties": [],
      "initialVariables": []
    },
    {
      "angle": 270,
      "customSize": false,
      "height": 0,
      "keepRatio": true,
      "layer": "",
      "name": "Wall",
      "persistentUuid": "3f7aa9e5-5db1-4980-b4ec-ba2636db7f25",
      "width": 0,
      "x": 32,
      "y": 1184,
      "zOrder": 1,
      "numberProperties": [],
      "stringProperties": [],
      "initialVariables": []
    },
    {
      "angle": 270,
      "customSize": false,
      "height": 0,
      "keepRatio": true,
      "layer": "",
      "name": "Wall",
      "persistentUuid": "796c71bc-45f2-452e-a9eb-21bcd542a78c",
      "width": 0,
      "x": 32,
      "y": 1120,
      "zOrder": 1,
      "numberProperties": [],
      "stringProperties": [],
      "initialVariables": []
    },
    {
      "angle": 270,
      "customSize": false,
      "height": 0,
      "keepRatio": true,
      "layer": "",
      "name": "Wall",
      "persistentUuid": "cdfb6b37-6e63-4a82-b794-7d61013300de",
      "width": 0,
      "x": 32,
      "y": 1056,
      "zOrder": 1,
      "numberProperties": [],
      "stringProperties": [],
      "initialVariables": []
    },
    {
      "angle": 270,
      "customSize": false,
      "height": 0,
      "keepRatio": true,
      "layer": "",
      "name": "Wall",
      "persistentUuid": "3e6105d7-17f3-450a-98b6-44c3ff19c436",
      "width": 0,
      "x": 32,
      "y": 992,
      "zOrder": 1,
      "numberProperties": [],
      "stringProperties": [],
      "initialVariables": []
    },
    {
      "angle": 270,
      "customSize": false,
      "height": 0,
      "keepRatio": true,
      "layer": "",
      "name": "Wall",
      "persistentUuid": "d11c5152-70fa-4688-8169-032c8fa61df4",
      "width": 0,
      "x": 32,
      "y": 928,
      "zOrder": 1,
      "numberProperties": [],
      "stringProperties": [],
      "initialVariables": []
    },
    {
      "angle": 270,
      "customSize": false,
      "height": 0,
      "keepRatio": true,
      "layer": "",
      "name": "Wall",
      "persistentUuid": "b8e915a8-a871-4a11-bdcd-e0643b3e76d5",
      "width": 0,
      "x": 32,
      "y": 864,
      "zOrder": 1,
      "numberProperties": [],
      "stringProperties": [],
      "initialVariables": []
    },
    {
      "angle": 270,
      "customSize": false,
      "height": 0,
      "keepRatio": true,
      "layer": "",
      "name": "Wall",
      "persistentUuid": "19b4b25a-b018-4dba-b121-cc9795569fc2",
      "width": 0,
      "x": 32,
      "y": 800,
      "zOrder": 1,
      "numberProperties": [],
      "stringProperties": [],
      "initialVariables": []
    },
    {
      "angle": 0,
      "customSize": false,
      "height": 0,
      "keepRatio": true,
      "layer": "",
      "name": "Wall",
      "persistentUuid": "2f6ee760-3d79-4812-8234-8f5680319176",
      "width": 0,
      "x": 96,
      "y": 1248,
      "zOrder": 1,
      "numberProperties": [],
      "stringProperties": [],
      "initialVariables": []
    },
    {
      "angle": 0,
      "customSize": false,
      "height": 0,
      "keepRatio": true,
      "layer": "",
      "name": "Wall",
      "persistentUuid": "3e920df9-1086-48a8-b242-3a9b114a1445",
      "width": 0,
      "x": 160,
      "y": 1248,
      "zOrder": 1,
      "numberProperties": [],
      "stringProperties": [],
      "initialVariables": []
    },
    {
      "angle": 0,
      "customSize": false,
      "height": 0,
      "keepRatio": true,
      "layer": "",
      "name": "Wall",
      "persistentUuid": "96423026-16a5-415c-b6f9-fcc36fce450c",
      "width": 0,
      "x": 224,
      "y": 1248,
      "zOrder": 1,
      "numberProperties": [],
      "stringProperties": [],
      "initialVariables": []
    },
    {
      "angle": 0,
      "customSize": false,
      "height": 0,
      "keepRatio": true,
      "layer": "",
      "name": "Wall",
      "persistentUuid": "4fd3ba3e-d30f-4c23-a9f9-fe3aae393a7f",
      "width": 0,
      "x": 288,
      "y": 1248,
      "zOrder": 1,
      "numberProperties": [],
      "stringProperties": [],
      "initialVariables": []
    },
    {
      "angle": 0,
      "customSize": false,
      "height": 0,
      "keepRatio": true,
      "layer": "",
      "name": "Wall",
      "persistentUuid": "6e54ebc8-00ff-4d51-a153-7a37222b8831",
      "width": 0,
      "x": 352,
      "y": 1248,
      "zOrder": 1,
      "numberProperties": [],
      "stringProperties": [],
      "initialVariables": []
    },
    {
      "angle": 0,
      "customSize": false,
      "height": 0,
      "keepRatio": true,
      "layer": "",
      "name": "Wall",
      "persistentUuid": "a3691a59-a510-4e83-a251-a0d1d204cd7f",
      "width": 0,
      "x": 416,
      "y": 1248,
      "zOrder": 1,
      "numberProperties": [],
      "stringProperties": [],
      "initialVariables": []
    },
    {
      "angle": 0,
      "customSize": false,
      "height": 0,
      "keepRatio": true,
      "layer": "",
      "name": "Wall",
      "persistentUuid": "c3eb5e7a-ea49-40fe-be6d-72a2961b6484",
      "width": 0,
      "x": 480,
      "y": 1248,
      "zOrder": 1,
      "numberProperties": [],
      "stringProperties": [],
      "initialVariables": []
    },
    {
      "angle": 0,
      "customSize": false,
      "height": 0,
      "keepRatio": true,
      "layer": "",
      "name": "Wall",
      "persistentUuid": "b6842e9d-7d05-4675-a378-ab4186940feb",
      "width": 0,
      "x": 544,
      "y": 1248,
      "zOrder": 1,
      "numberProperties": [],
      "stringProperties": [],
      "initialVariables": []
    },
    {
      "angle": 270,
      "customSize": false,
      "height": 0,
      "keepRatio": true,
      "layer": "",
      "name": "Wall",
      "persistentUuid": "8ad8b69b-04bd-4a58-86fd-e0143863e746",
      "width": 0,
      "x": 32,
      "y": 736,
      "zOrder": 1,
      "numberProperties": [],
      "stringProperties": [],
      "initialVariables": []
    },
    {
      "angle": 180,
      "customSize": false,
      "height": 0,
      "keepRatio": true,
      "layer": "",
      "name": "Wall",
      "persistentUuid": "fc3f67a1-5d1b-46d4-892d-d203ac2bc2ff",
      "width": 0,
      "x": 1248,
      "y": 1248,
      "zOrder": 1,
      "numberProperties": [],
      "stringProperties": [],
      "initialVariables": []
    },
    {
      "angle": 180,
      "customSize": false,
      "height": 0,
      "keepRatio": true,
      "layer": "",
      "name": "Wall",
      "persistentUuid": "86ececac-5396-4294-bfa4-f54601865f8e",
      "width": 0,
      "x": 1184,
      "y": 1248,
      "zOrder": 1,
      "numberProperties": [],
      "stringProperties": [],
      "initialVariables": []
    },
    {
      "angle": 180,
      "customSize": false,
      "height": 0,
      "keepRatio": true,
      "layer": "",
      "name": "Wall",
      "persistentUuid": "b6186226-0d39-4885-ad92-67df7d573a32",
      "width": 0,
      "x": 1120,
      "y": 1248,
      "zOrder": 1,
      "numberProperties": [],
      "stringProperties": [],
      "initialVariables": []
    },
    {
      "angle": 180,
      "customSize": false,
      "height": 0,
      "keepRatio": true,
      "layer": "",
      "name": "Wall",
      "persistentUuid": "5f3e9a52-d000-4cd4-a81b-c398ecb53925",
      "width": 0,
      "x": 1056,
      "y": 1248,
      "zOrder": 1,
      "numberProperties": [],
      "stringProperties": [],
      "initialVariables": []
    },
    {
      "angle": 180,
      "customSize": false,
      "height": 0,
      "keepRatio": true,
      "layer": "",
      "name": "Wall",
      "persistentUuid": "e061cd67-a7eb-453a-86ec-4489ac14c647",
      "width": 0,
      "x": 992,
      "y": 1248,
      "zOrder": 1,
      "numberProperties": [],
      "stringProperties": [],
      "initialVariables": []
    },
    {
      "angle": 180,
      "customSize": false,
      "height": 0,
      "keepRatio": true,
      "layer": "",
      "name": "Wall",
      "persistentUuid": "32fa2719-49a6-4990-8368-4d12aa7198e8",
      "width": 0,
      "x": 928,
      "y": 1248,
      "zOrder": 1,
      "numberProperties": [],
      "stringProperties": [],
      "initialVariables": []
    },
    {
      "angle": 180,
      "customSize": false,
      "height": 0,
      "keepRatio": true,
      "layer": "",
      "name": "Wall",
      "persistentUuid": "70047ab8-bdea-4b5f-af7d-3effa7aa0835",
      "width": 0,
      "x": 864,
      "y": 1248,
      "zOrder": 1,
      "numberProperties": [],
      "stringProperties": [],
      "initialVariables": []
    },
    {
      "angle": 180,
      "customSize": false,
      "height": 0,
      "keepRatio": true,
      "layer": "",
      "name": "Wall",
      "persistentUuid": "6d8be3d0-5aeb-47cc-a653-92a6ed473f9e",
      "width": 0,
      "x": 800,
      "y": 1248,
      "zOrder": 1,
      "numberProperties": [],
      "stringProperties": [],
      "initialVariables": []
    },
    {
      "angle": 270,
      "customSize": false,
      "height": 0,
      "keepRatio": true,
      "layer": "",
      "name": "Wall",
      "persistentUuid": "4f86d017-e998-440e-b805-e132cb3b744f",
      "width": 0,
      "x": 1248,
      "y": 1184,
      "zOrder": 1,
      "numberProperties": [],
      "stringProperties": [],
      "initialVariables": []
    },
    {
      "angle": 270,
      "customSize": false,
      "height": 0,
      "keepRatio": true,
      "layer": "",
      "name": "Wall",
      "persistentUuid": "55b3f92d-50b2-4f3d-bdcb-b92725977c8f",
      "width": 0,
      "x": 1248,
      "y": 1120,
      "zOrder": 1,
      "numberProperties": [],
      "stringProperties": [],
      "initialVariables": []
    },
    {
      "angle": 270,
      "customSize": false,
      "height": 0,
      "keepRatio": true,
      "layer": "",
      "name": "Wall",
      "persistentUuid": "f275fb0d-7da8-4f97-99a8-db2a06345ec2",
      "width": 0,
      "x": 1248,
      "y": 1056,
      "zOrder": 1,
      "numberProperties": [],
      "stringProperties": [],
      "initialVariables": []
    },
    {
      "angle": 270,
      "customSize": false,
      "height": 0,
      "keepRatio": true,
      "layer": "",
      "name": "Wall",
      "persistentUuid": "e82ba324-df07-45c1-b56b-cdee9749e794",
      "width": 0,
      "x": 1248,
      "y": 992,
      "zOrder": 1,
      "numberProperties": [],
      "stringProperties": [],
      "initialVariables": []
    },
    {
      "angle": 270,
      "customSize": false,
      "height": 0,
      "keepRatio": true,
      "layer": "",
      "name": "Wall",
      "persistentUuid": "41e85619-24e4-4537-b642-5642958e49ff",
      "width": 0,
      "x": 1248,
      "y": 928,
      "zOrder": 1,
      "numberProperties": [],
      "stringProperties": [],
      "initialVariables": []
    },
    {
      "angle": 270,
      "customSize": false,
      "height": 0,
      "keepRatio": true,
      "layer": "",
      "name": "Wall",
      "persistentUuid": "9a2ce947-45aa-4402-9518-a85b76200574",
      "width": 0,
      "x": 1248,
      "y": 864,
      "zOrder": 1,
      "numberProperties": [],
      "stringProperties": [],
      "initialVariables": []
    },
    {
      "angle": 270,
      "customSize": false,
      "height": 0,
      "keepRatio": true,
      "layer": "",
      "name": "Wall",
      "persistentUuid": "d3a904bb-eb03-490b-bd29-e758e0877f5c",
      "width": 0,
      "x": 1248,
      "y": 800,
      "zOrder": 1,
      "numberProperties": [],
      "stringProperties": [],
      "initialVariables": []
    },
    {
      "angle": 270,
      "customSize": false,
      "height": 0,
      "keepRatio": true,
      "layer": "",
      "name": "Wall",
      "persistentUuid": "1ffedd88-08a8-4d8d-aa67-dafe28804cc4",
      "width": 0,
      "x": 1248,
      "y": 736,
      "zOrder": 1,
      "numberProperties": [],
      "stringProperties": [],
      "initialVariables": []
    },
    {
      "angle": 180,
      "customSize": false,
      "height": 0,
      "keepRatio": true,
      "layer": "",
      "name": "Wall",
      "persistentUuid": "e574dbf8-a10e-4468-af25-d6144caa7b3c",
      "width": 0,
      "x": 736,
      "y": 1248,
      "zOrder": 1,
      "numberProperties": [],
      "stringProperties": [],
      "initialVariables": []
    },
    {
      "angle": 90,
      "customSize": false,
      "height": 0,
      "keepRatio": true,
      "layer": "",
      "name": "Wall",
      "persistentUuid": "aa730d62-b967-4962-911f-9dee3e1f0b34",
      "width": 0,
      "x": 1248,
      "y": 32,
      "zOrder": 1,
      "numberProperties": [],
      "stringProperties": [],
      "initialVariables": []
    },
    {
      "angle": 90,
      "customSize": false,
      "height": 0,
      "keepRatio": true,
      "layer": "",
      "name": "Wall",
      "persistentUuid": "20815daa-a45f-484c-b55c-ead04be8462a",
      "width": 0,
      "x": 1248,
      "y": 96,
      "zOrder": 1,
      "numberProperties": [],
      "stringProperties": [],
      "initialVariables": []
    },
    {
      "angle": 90,
      "customSize": false,
      "height": 0,
      "keepRatio": true,
      "layer": "",
      "name": "Wall",
      "persistentUuid": "fa1f13f8-30b8-47a2-ba4f-9e2e25ca4bb0",
      "width": 0,
      "x": 1248,
      "y": 160,
      "zOrder": 1,
      "numberProperties": [],
      "stringProperties": [],
      "initialVariables": []
    },
    {
      "angle": 90,
      "customSize": false,
      "height": 0,
      "keepRatio": true,
      "layer": "",
      "name": "Wall",
      "persistentUuid": "2f8ca041-373d-4b24-ae0b-81014ac1bdd2",
      "width": 0,
      "x": 1248,
      "y": 224,
      "zOrder": 1,
      "numberProperties": [],
      "stringProperties": [],
      "initialVariables": []
    },
    {
      "angle": 90,
      "customSize": false,
      "height": 0,
      "keepRatio": true,
      "layer": "",
      "name": "Wall",
      "persistentUuid": "b88148fb-d7d0-404e-97c7-e12c3a83c052",
      "width": 0,
      "x": 1248,
      "y": 288,
      "zOrder": 1,
      "numberProperties": [],
      "stringProperties": [],
      "initialVariables": []
    },
    {
      "angle": 90,
      "customSize": false,
      "height": 0,
      "keepRatio": true,
      "layer": "",
      "name": "Wall",
      "persistentUuid": "bf593292-0870-49e2-9d58-85082469473a",
      "width": 0,
      "x": 1248,
      "y": 352,
      "zOrder": 1,
      "numberProperties": [],
      "stringProperties": [],
      "initialVariables": []
    },
    {
      "angle": 90,
      "customSize": false,
      "height": 0,
      "keepRatio": true,
      "layer": "",
      "name": "Wall",
      "persistentUuid": "745efe18-d815-4749-acbd-9926636d417e",
      "width": 0,
      "x": 1248,
      "y": 416,
      "zOrder": 1,
      "numberProperties": [],
      "stringProperties": [],
      "initialVariables": []
    },
    {
      "angle": 90,
      "customSize": false,
      "height": 0,
      "keepRatio": true,
      "layer": "",
      "name": "Wall",
      "persistentUuid": "71c56d07-a8db-45c9-8a61-eaaa550324ac",
      "width": 0,
      "x": 1248,
      "y": 480,
      "zOrder": 1,
      "numberProperties": [],
      "stringProperties": [],
      "initialVariables": []
    },
    {
      "angle": 180,
      "customSize": false,
      "height": 0,
      "keepRatio": true,
      "layer": "",
      "name": "Wall",
      "persistentUuid": "aedc3925-b428-4909-a93d-26459040f0a7",
      "width": 0,
      "x": 1184,
      "y": 32,
      "zOrder": 1,
      "numberProperties": [],
      "stringProperties": [],
      "initialVariables": []
    },
    {
      "angle": 180,
      "customSize": false,
      "height": 0,
      "keepRatio": true,
      "layer": "",
      "name": "Wall",
      "persistentUuid": "a136ce21-52dc-47c5-ae15-67ce87deaace",
      "width": 0,
      "x": 1120,
      "y": 32,
      "zOrder": 1,
      "numberProperties": [],
      "stringProperties": [],
      "initialVariables": []
    },
    {
      "angle": 180,
      "customSize": false,
      "height": 0,
      "keepRatio": true,
      "layer": "",
      "name": "Wall",
      "persistentUuid": "700886dc-05c8-457e-a3b9-acf841ac6716",
      "width": 0,
      "x": 1056,
      "y": 32,
      "zOrder": 1,
      "numberProperties": [],
      "stringProperties": [],
      "initialVariables": []
    },
    {
      "angle": 180,
      "customSize": false,
      "height": 0,
      "keepRatio": true,
      "layer": "",
      "name": "Wall",
      "persistentUuid": "74a89512-ccef-46c1-95e2-bd4e139d04d0",
      "width": 0,
      "x": 992,
      "y": 32,
      "zOrder": 1,
      "numberProperties": [],
      "stringProperties": [],
      "initialVariables": []
    },
    {
      "angle": 180,
      "customSize": false,
      "height": 0,
      "keepRatio": true,
      "layer": "",
      "name": "Wall",
      "persistentUuid": "99732d79-e157-4990-ac98-7c0a03b41be4",
      "width": 0,
      "x": 928,
      "y": 32,
      "zOrder": 1,
      "numberProperties": [],
      "stringProperties": [],
      "initialVariables": []
    },
    {
      "angle": 180,
      "customSize": false,
      "height": 0,
      "keepRatio": true,
      "layer": "",
      "name": "Wall",
      "persistentUuid": "aa51d9e3-cbb0-4ee3-9117-b542c4ad2858",
      "width": 0,
      "x": 864,
      "y": 32,
      "zOrder": 1,
      "numberProperties": [],
      "stringProperties": [],
      "initialVariables": []
    },
    {
      "angle": 180,
      "customSize": false,
      "height": 0,
      "keepRatio": true,
      "layer": "",
      "name": "Wall",
      "persistentUuid": "f876c37d-4899-46ec-ba9f-e626c07ee0e4",
      "width": 0,
      "x": 800,
      "y": 32,
      "zOrder": 1,
      "numberProperties": [],
      "stringProperties": [],
      "initialVariables": []
    },
    {
      "angle": 180,
      "customSize": false,
      "height": 0,
      "keepRatio": true,
      "layer": "",
      "name": "Wall",
      "persistentUuid": "1675da93-1987-4729-ad2b-4052a9d1a97b",
      "width": 0,
      "x": 736,
      "y": 32,
      "zOrder": 1,
      "numberProperties": [],
      "stringProperties": [],
      "initialVariables": []
    },
    {
      "angle": 90,
      "customSize": false,
      "height": 0,
      "keepRatio": true,
      "layer": "",
      "name": "Wall",
      "persistentUuid": "f2e09823-42b9-4a23-b4c4-4246cda18798",
      "width": 0,
      "x": 1248,
      "y": 544,
      "zOrder": 1,
      "numberProperties": [],
      "stringProperties": [],
      "initialVariables": []
    },
    {
      "angle": 0,
      "customSize": true,
      "depth": 1,
      "height": 1152,
      "keepRatio": true,
      "layer": "",
      "name": "overlapChecker",
      "persistentUuid": "3c13db6a-778f-43a6-9204-8bfb35b13313",
      "width": 1152,
      "x": 64,
      "y": 64,
      "z": -3,
      "zOrder": 2,
      "numberProperties": [],
      "stringProperties": [],
      "initialVariables": []
    },
    {
      "angle": 0,
      "customSize": false,
      "height": 0,
      "keepRatio": true,
      "layer": "",
      "name": "interiorGenerator",
      "persistentUuid": "073e0f08-903d-438c-aeed-66dfaed60430",
      "width": 0,
      "x": 64,
      "y": 64,
      "zOrder": 3,
      "numberProperties": [],
      "stringProperties": [],
      "initialVariables": []
    },
    {
      "angle": 0,
      "customSize": false,
      "height": 0,
      "keepRatio": true,
      "layer": "",
      "name": "Up",
      "persistentUuid": "6f4060e3-a334-467d-b369-8658fabd74cf",
      "width": 0,
      "x": 0,
      "y": -1280,
      "zOrder": 4,
      "numberProperties": [],
      "stringProperties": [],
      "initialVariables": []
    },
    {
      "angle": 0,
      "customSize": false,
      "height": 0,
      "keepRatio": true,
      "layer": "",
      "name": "Down",
      "persistentUuid": "6440b37c-19b9-4bfc-bc7b-ef3cebd82216",
      "width": 0,
      "x": 0,
      "y": 1280,
      "zOrder": 5,
      "numberProperties": [],
      "stringProperties": [],
      "initialVariables": []
    },
    {
      "angle": 0,
      "customSize": false,
      "height": 0,
      "keepRatio": true,
      "layer": "",
      "name": "Right",
      "persistentUuid": "51ec9647-47d8-4f32-9f62-08ee749c033b",
      "width": 0,
      "x": 1280,
      "y": 0,
      "zOrder": 6,
      "numberProperties": [],
      "stringProperties": [],
      "initialVariables": []
    },
    {
      "angle": 0,
      "customSize": false,
      "height": 0,
      "keepRatio": true,
      "layer": "",
      "name": "Left",
      "persistentUuid": "9978acd0-7e41-4a63-b2f4-990bc5cd7ce2",
      "width": 0,
      "x": -1280,
      "y": 0,
      "zOrder": 7,
      "numberProperties": [],
      "stringProperties": [],
      "initialVariables": []
    }
  ],
  "editionSettings": {
    "grid": true,
    "gridType": "rectangular",
    "gridWidth": 64,
    "gridHeight": 64,
    "gridOffsetX": 0,
    "gridOffsetY": 0,
    "gridColor": 10401023,
    "gridAlpha": 0.8,
    "snap": true,
    "zoomFactor": 0.17228927016997694,
    "windowMask": false
  }
}